{
  "version": 1,
  "project_id": "parse-parity-fixture",
  "speaker": "Base02",
  "source_audio": "audio/original/Base02/source.wav",
  "source_audio_duration_sec": 0.1,
  "tiers": {
    "ipa": {
      "display_order": 1,
      "type": "interval",
      "intervals": [
        {
          "start": 0.0,
          "end": 0.1,
          "text": "aʂ"
        }
      ]
    },
    "ortho": {
      "display_order": 2,
      "type": "interval",
      "intervals": [
        {
          "start": 0.0,
          "end": 0.1,
          "text": "aş"
        }
      ]
    },
    "concept": {
      "display_order": 3,
      "type": "interval",
      "intervals": [
        {
          "start": 0.0,
          "end": 0.1,
          "text": "1: ash"
        }
      ]
    },
    "speaker": {
      "display_order": 4,
      "type": "interval",
      "intervals": [
        {
          "start": 0.0,
          "end": 0.1,
          "text": "Base02"
        }
      ]
    }
  },
  "metadata": {
    "language_code": "sdh",
    "created": "2026-01-01T00:00:10Z",
    "modified": "2026-01-01T00:00:10Z"
  }
}
